{
    "schema":{
        "fields":[
            {
                "name":"index",
                "type":"integer"
            },
            {
                "name":"sort",
                "type":"string"
            },
            {
                "name":"name",
                "type":"string"
            },
            {
                "name":"search_code",
                "type":"string"
            },
            {
                "name":"apt_type",
                "type":"string"
            },
            {
                "name":"apt_year",
                "type":"number"
            },
            {
                "name":"value_score",
                "type":"number"
            },
            {
                "name":"region",
                "type":"string"
            },
            {
                "name":"region_code",
                "type":"string"
            },
            {
                "name":"sub_region_code",
                "type":"string"
            },
            {
                "name":"shorten_url",
                "type":"string"
            }
        ],
        "primaryKey":[
            "index"
        ],
        "pandas_version":"1.4.0"
    },
    "data":[
        {
            "index":0,
            "sort":"balanced",
            "name":"가평자이",
            "search_code":"139287",
            "apt_type":"아파트",
            "apt_year":1.0,
            "value_score":32.5972,
            "region":"경기도 가평군",
            "region_code":"Gyeonggi",
            "sub_region_code":"4182000000_Gyeonggi_Gapyeong",
            "shorten_url":"https:\/\/me2.do\/5S9oEjIS"
        },
        {
            "index":1,
            "sort":"balanced",
            "name":"청평삼성쉐르빌",
            "search_code":"102612",
            "apt_type":"아파트",
            "apt_year":12.0,
            "value_score":31.26,
            "region":"경기도 가평군",
            "region_code":"Gyeonggi",
            "sub_region_code":"4182000000_Gyeonggi_Gapyeong",
            "shorten_url":"https:\/\/me2.do\/5S9oEjIS"
        },
        {
            "index":2,
            "sort":"balanced",
            "name":"청평세양청마루",
            "search_code":"25840",
            "apt_type":"아파트",
            "apt_year":17.0,
            "value_score":28.04,
            "region":"경기도 가평군",
            "region_code":"Gyeonggi",
            "sub_region_code":"4182000000_Gyeonggi_Gapyeong",
            "shorten_url":"https:\/\/me2.do\/5S9oEjIS"
        },
        {
            "index":3,
            "sort":"balanced",
            "name":"e편한세상가평퍼스트원",
            "search_code":"139288",
            "apt_type":"아파트",
            "apt_year":1.0,
            "value_score":27.8872,
            "region":"경기도 가평군",
            "region_code":"Gyeonggi",
            "sub_region_code":"4182000000_Gyeonggi_Gapyeong",
            "shorten_url":"https:\/\/me2.do\/5S9oEjIS"
        },
        {
            "index":4,
            "sort":"balanced",
            "name":"청평경남아너스빌",
            "search_code":"25896",
            "apt_type":"아파트",
            "apt_year":16.0,
            "value_score":27.14,
            "region":"경기도 가평군",
            "region_code":"Gyeonggi",
            "sub_region_code":"4182000000_Gyeonggi_Gapyeong",
            "shorten_url":"https:\/\/me2.do\/5S9oEjIS"
        },
        {
            "index":5,
            "sort":"balanced",
            "name":"청평청구",
            "search_code":"14455",
            "apt_type":"아파트",
            "apt_year":26.0,
            "value_score":27.12,
            "region":"경기도 가평군",
            "region_code":"Gyeonggi",
            "sub_region_code":"4182000000_Gyeonggi_Gapyeong",
            "shorten_url":"https:\/\/me2.do\/5S9oEjIS"
        },
        {
            "index":6,
            "sort":"balanced",
            "name":"힐스테이트가평더뉴클래스",
            "search_code":"144185",
            "apt_type":"아파트",
            "apt_year":1.0,
            "value_score":26.9872,
            "region":"경기도 가평군",
            "region_code":"Gyeonggi",
            "sub_region_code":"4182000000_Gyeonggi_Gapyeong",
            "shorten_url":"https:\/\/me2.do\/5S9oEjIS"
        },
        {
            "index":7,
            "sort":"balanced",
            "name":"가평설악디엘본",
            "search_code":"147989",
            "apt_type":"분양권",
            "apt_year":0.0,
            "value_score":26.2216,
            "region":"경기도 가평군",
            "region_code":"Gyeonggi",
            "sub_region_code":"4182000000_Gyeonggi_Gapyeong",
            "shorten_url":"https:\/\/me2.do\/5S9oEjIS"
        },
        {
            "index":8,
            "sort":"balanced",
            "name":"가평센트럴파크더스카이(주상복합)",
            "search_code":"135203",
            "apt_type":"아파트",
            "apt_year":2.0,
            "value_score":25.3472,
            "region":"경기도 가평군",
            "region_code":"Gyeonggi",
            "sub_region_code":"4182000000_Gyeonggi_Gapyeong",
            "shorten_url":"https:\/\/me2.do\/5S9oEjIS"
        },
        {
            "index":9,
            "sort":"balanced",
            "name":"가평선힐",
            "search_code":"24038",
            "apt_type":"아파트",
            "apt_year":16.0,
            "value_score":24.7972,
            "region":"경기도 가평군",
            "region_code":"Gyeonggi",
            "sub_region_code":"4182000000_Gyeonggi_Gapyeong",
            "shorten_url":"https:\/\/me2.do\/5S9oEjIS"
        },
        {
            "index":10,
            "sort":"living",
            "name":"가평자이",
            "search_code":"139287",
            "apt_type":"아파트",
            "apt_year":1.0,
            "value_score":45.8496,
            "region":"경기도 가평군",
            "region_code":"Gyeonggi",
            "sub_region_code":"4182000000_Gyeonggi_Gapyeong",
            "shorten_url":"https:\/\/me2.do\/5S9oEjIS"
        },
        {
            "index":11,
            "sort":"living",
            "name":"e편한세상가평퍼스트원",
            "search_code":"139288",
            "apt_type":"아파트",
            "apt_year":1.0,
            "value_score":44.9496,
            "region":"경기도 가평군",
            "region_code":"Gyeonggi",
            "sub_region_code":"4182000000_Gyeonggi_Gapyeong",
            "shorten_url":"https:\/\/me2.do\/5S9oEjIS"
        },
        {
            "index":12,
            "sort":"living",
            "name":"힐스테이트가평더뉴클래스",
            "search_code":"144185",
            "apt_type":"아파트",
            "apt_year":1.0,
            "value_score":44.3496,
            "region":"경기도 가평군",
            "region_code":"Gyeonggi",
            "sub_region_code":"4182000000_Gyeonggi_Gapyeong",
            "shorten_url":"https:\/\/me2.do\/5S9oEjIS"
        },
        {
            "index":13,
            "sort":"living",
            "name":"청평삼성쉐르빌",
            "search_code":"102612",
            "apt_type":"아파트",
            "apt_year":12.0,
            "value_score":42.2,
            "region":"경기도 가평군",
            "region_code":"Gyeonggi",
            "sub_region_code":"4182000000_Gyeonggi_Gapyeong",
            "shorten_url":"https:\/\/me2.do\/5S9oEjIS"
        },
        {
            "index":14,
            "sort":"living",
            "name":"가평설악디엘본",
            "search_code":"147989",
            "apt_type":"분양권",
            "apt_year":0.0,
            "value_score":40.8788,
            "region":"경기도 가평군",
            "region_code":"Gyeonggi",
            "sub_region_code":"4182000000_Gyeonggi_Gapyeong",
            "shorten_url":"https:\/\/me2.do\/5S9oEjIS"
        },
        {
            "index":15,
            "sort":"living",
            "name":"가평설악엘크루",
            "search_code":"f9824",
            "apt_type":"분양(예정)",
            "apt_year":-2.0,
            "value_score":37.8388,
            "region":"경기도 가평군",
            "region_code":"Gyeonggi",
            "sub_region_code":"4182000000_Gyeonggi_Gapyeong",
            "shorten_url":"https:\/\/me2.do\/5S9oEjIS"
        },
        {
            "index":16,
            "sort":"living",
            "name":"가평코아루",
            "search_code":"127107",
            "apt_type":"아파트",
            "apt_year":3.0,
            "value_score":36.3996,
            "region":"경기도 가평군",
            "region_code":"Gyeonggi",
            "sub_region_code":"4182000000_Gyeonggi_Gapyeong",
            "shorten_url":"https:\/\/me2.do\/5S9oEjIS"
        },
        {
            "index":17,
            "sort":"living",
            "name":"가평블루핀",
            "search_code":"122643",
            "apt_type":"아파트",
            "apt_year":5.0,
            "value_score":33.1996,
            "region":"경기도 가평군",
            "region_code":"Gyeonggi",
            "sub_region_code":"4182000000_Gyeonggi_Gapyeong",
            "shorten_url":"https:\/\/me2.do\/5S9oEjIS"
        },
        {
            "index":18,
            "sort":"living",
            "name":"가평센트럴파크더스카이(주상복합)",
            "search_code":"135203",
            "apt_type":"아파트",
            "apt_year":2.0,
            "value_score":33.1496,
            "region":"경기도 가평군",
            "region_code":"Gyeonggi",
            "sub_region_code":"4182000000_Gyeonggi_Gapyeong",
            "shorten_url":"https:\/\/me2.do\/5S9oEjIS"
        },
        {
            "index":19,
            "sort":"living",
            "name":"청평세양청마루",
            "search_code":"25840",
            "apt_type":"아파트",
            "apt_year":17.0,
            "value_score":32.17,
            "region":"경기도 가평군",
            "region_code":"Gyeonggi",
            "sub_region_code":"4182000000_Gyeonggi_Gapyeong",
            "shorten_url":"https:\/\/me2.do\/5S9oEjIS"
        },
        {
            "index":20,
            "sort":"transport",
            "name":"가평자이",
            "search_code":"139287",
            "apt_type":"아파트",
            "apt_year":1.0,
            "value_score":31.9572,
            "region":"경기도 가평군",
            "region_code":"Gyeonggi",
            "sub_region_code":"4182000000_Gyeonggi_Gapyeong",
            "shorten_url":"https:\/\/me2.do\/5S9oEjIS"
        },
        {
            "index":21,
            "sort":"transport",
            "name":"청평삼성쉐르빌",
            "search_code":"102612",
            "apt_type":"아파트",
            "apt_year":12.0,
            "value_score":31.02,
            "region":"경기도 가평군",
            "region_code":"Gyeonggi",
            "sub_region_code":"4182000000_Gyeonggi_Gapyeong",
            "shorten_url":"https:\/\/me2.do\/5S9oEjIS"
        },
        {
            "index":22,
            "sort":"transport",
            "name":"청평세양청마루",
            "search_code":"25840",
            "apt_type":"아파트",
            "apt_year":17.0,
            "value_score":28.515,
            "region":"경기도 가평군",
            "region_code":"Gyeonggi",
            "sub_region_code":"4182000000_Gyeonggi_Gapyeong",
            "shorten_url":"https:\/\/me2.do\/5S9oEjIS"
        },
        {
            "index":23,
            "sort":"transport",
            "name":"청평경남아너스빌",
            "search_code":"25896",
            "apt_type":"아파트",
            "apt_year":16.0,
            "value_score":27.915,
            "region":"경기도 가평군",
            "region_code":"Gyeonggi",
            "sub_region_code":"4182000000_Gyeonggi_Gapyeong",
            "shorten_url":"https:\/\/me2.do\/5S9oEjIS"
        },
        {
            "index":24,
            "sort":"transport",
            "name":"청평청구",
            "search_code":"14455",
            "apt_type":"아파트",
            "apt_year":26.0,
            "value_score":27.005,
            "region":"경기도 가평군",
            "region_code":"Gyeonggi",
            "sub_region_code":"4182000000_Gyeonggi_Gapyeong",
            "shorten_url":"https:\/\/me2.do\/5S9oEjIS"
        },
        {
            "index":25,
            "sort":"transport",
            "name":"가평선힐",
            "search_code":"24038",
            "apt_type":"아파트",
            "apt_year":16.0,
            "value_score":26.1072,
            "region":"경기도 가평군",
            "region_code":"Gyeonggi",
            "sub_region_code":"4182000000_Gyeonggi_Gapyeong",
            "shorten_url":"https:\/\/me2.do\/5S9oEjIS"
        },
        {
            "index":26,
            "sort":"transport",
            "name":"e편한세상가평퍼스트원",
            "search_code":"139288",
            "apt_type":"아파트",
            "apt_year":1.0,
            "value_score":24.9372,
            "region":"경기도 가평군",
            "region_code":"Gyeonggi",
            "sub_region_code":"4182000000_Gyeonggi_Gapyeong",
            "shorten_url":"https:\/\/me2.do\/5S9oEjIS"
        },
        {
            "index":27,
            "sort":"transport",
            "name":"유성",
            "search_code":"24164",
            "apt_type":"아파트",
            "apt_year":31.0,
            "value_score":24.7872,
            "region":"경기도 가평군",
            "region_code":"Gyeonggi",
            "sub_region_code":"4182000000_Gyeonggi_Gapyeong",
            "shorten_url":"https:\/\/me2.do\/5S9oEjIS"
        },
        {
            "index":28,
            "sort":"transport",
            "name":"세대넥스빌",
            "search_code":"14452",
            "apt_type":"아파트",
            "apt_year":28.0,
            "value_score":24.5172,
            "region":"경기도 가평군",
            "region_code":"Gyeonggi",
            "sub_region_code":"4182000000_Gyeonggi_Gapyeong",
            "shorten_url":"https:\/\/me2.do\/5S9oEjIS"
        },
        {
            "index":29,
            "sort":"transport",
            "name":"신초",
            "search_code":"23686",
            "apt_type":"아파트",
            "apt_year":31.0,
            "value_score":24.5172,
            "region":"경기도 가평군",
            "region_code":"Gyeonggi",
            "sub_region_code":"4182000000_Gyeonggi_Gapyeong",
            "shorten_url":"https:\/\/me2.do\/5S9oEjIS"
        },
        {
            "index":30,
            "sort":"infra",
            "name":"태광",
            "search_code":"15866",
            "apt_type":"아파트",
            "apt_year":32.0,
            "value_score":29.912,
            "region":"경기도 가평군",
            "region_code":"Gyeonggi",
            "sub_region_code":"4182000000_Gyeonggi_Gapyeong",
            "shorten_url":"https:\/\/me2.do\/5S9oEjIS"
        },
        {
            "index":31,
            "sort":"infra",
            "name":"준수",
            "search_code":"104812",
            "apt_type":"아파트",
            "apt_year":32.0,
            "value_score":27.912,
            "region":"경기도 가평군",
            "region_code":"Gyeonggi",
            "sub_region_code":"4182000000_Gyeonggi_Gapyeong",
            "shorten_url":"https:\/\/me2.do\/5S9oEjIS"
        },
        {
            "index":32,
            "sort":"infra",
            "name":"가평자이",
            "search_code":"139287",
            "apt_type":"아파트",
            "apt_year":1.0,
            "value_score":27.462,
            "region":"경기도 가평군",
            "region_code":"Gyeonggi",
            "sub_region_code":"4182000000_Gyeonggi_Gapyeong",
            "shorten_url":"https:\/\/me2.do\/5S9oEjIS"
        },
        {
            "index":33,
            "sort":"infra",
            "name":"청평삼성쉐르빌",
            "search_code":"102612",
            "apt_type":"아파트",
            "apt_year":12.0,
            "value_score":27.1,
            "region":"경기도 가평군",
            "region_code":"Gyeonggi",
            "sub_region_code":"4182000000_Gyeonggi_Gapyeong",
            "shorten_url":"https:\/\/me2.do\/5S9oEjIS"
        },
        {
            "index":34,
            "sort":"infra",
            "name":"가평센트럴파크더스카이(주상복합)",
            "search_code":"135203",
            "apt_type":"아파트",
            "apt_year":2.0,
            "value_score":27.012,
            "region":"경기도 가평군",
            "region_code":"Gyeonggi",
            "sub_region_code":"4182000000_Gyeonggi_Gapyeong",
            "shorten_url":"https:\/\/me2.do\/5S9oEjIS"
        },
        {
            "index":35,
            "sort":"infra",
            "name":"청평청구",
            "search_code":"14455",
            "apt_type":"아파트",
            "apt_year":26.0,
            "value_score":26.85,
            "region":"경기도 가평군",
            "region_code":"Gyeonggi",
            "sub_region_code":"4182000000_Gyeonggi_Gapyeong",
            "shorten_url":"https:\/\/me2.do\/5S9oEjIS"
        },
        {
            "index":36,
            "sort":"infra",
            "name":"청평세양청마루",
            "search_code":"25840",
            "apt_type":"아파트",
            "apt_year":17.0,
            "value_score":26.75,
            "region":"경기도 가평군",
            "region_code":"Gyeonggi",
            "sub_region_code":"4182000000_Gyeonggi_Gapyeong",
            "shorten_url":"https:\/\/me2.do\/5S9oEjIS"
        },
        {
            "index":37,
            "sort":"infra",
            "name":"형진",
            "search_code":"127696",
            "apt_type":"아파트",
            "apt_year":33.0,
            "value_score":26.612,
            "region":"경기도 가평군",
            "region_code":"Gyeonggi",
            "sub_region_code":"4182000000_Gyeonggi_Gapyeong",
            "shorten_url":"https:\/\/me2.do\/5S9oEjIS"
        },
        {
            "index":38,
            "sort":"infra",
            "name":"e편한세상가평퍼스트원",
            "search_code":"139288",
            "apt_type":"아파트",
            "apt_year":1.0,
            "value_score":26.112,
            "region":"경기도 가평군",
            "region_code":"Gyeonggi",
            "sub_region_code":"4182000000_Gyeonggi_Gapyeong",
            "shorten_url":"https:\/\/me2.do\/5S9oEjIS"
        },
        {
            "index":39,
            "sort":"infra",
            "name":"청평경남아너스빌",
            "search_code":"25896",
            "apt_type":"아파트",
            "apt_year":16.0,
            "value_score":25.25,
            "region":"경기도 가평군",
            "region_code":"Gyeonggi",
            "sub_region_code":"4182000000_Gyeonggi_Gapyeong",
            "shorten_url":"https:\/\/me2.do\/5S9oEjIS"
        },
        {
            "index":40,
            "sort":"education",
            "name":"가평자이",
            "search_code":"139287",
            "apt_type":"아파트",
            "apt_year":1.0,
            "value_score":38.004,
            "region":"경기도 가평군",
            "region_code":"Gyeonggi",
            "sub_region_code":"4182000000_Gyeonggi_Gapyeong",
            "shorten_url":"https:\/\/me2.do\/5S9oEjIS"
        },
        {
            "index":41,
            "sort":"education",
            "name":"e편한세상가평퍼스트원",
            "search_code":"139288",
            "apt_type":"아파트",
            "apt_year":1.0,
            "value_score":37.824,
            "region":"경기도 가평군",
            "region_code":"Gyeonggi",
            "sub_region_code":"4182000000_Gyeonggi_Gapyeong",
            "shorten_url":"https:\/\/me2.do\/5S9oEjIS"
        },
        {
            "index":42,
            "sort":"education",
            "name":"청평삼성쉐르빌",
            "search_code":"102612",
            "apt_type":"아파트",
            "apt_year":12.0,
            "value_score":37.28,
            "region":"경기도 가평군",
            "region_code":"Gyeonggi",
            "sub_region_code":"4182000000_Gyeonggi_Gapyeong",
            "shorten_url":"https:\/\/me2.do\/5S9oEjIS"
        },
        {
            "index":43,
            "sort":"education",
            "name":"힐스테이트가평더뉴클래스",
            "search_code":"144185",
            "apt_type":"아파트",
            "apt_year":1.0,
            "value_score":37.224,
            "region":"경기도 가평군",
            "region_code":"Gyeonggi",
            "sub_region_code":"4182000000_Gyeonggi_Gapyeong",
            "shorten_url":"https:\/\/me2.do\/5S9oEjIS"
        },
        {
            "index":44,
            "sort":"education",
            "name":"가평코아루",
            "search_code":"127107",
            "apt_type":"아파트",
            "apt_year":3.0,
            "value_score":34.524,
            "region":"경기도 가평군",
            "region_code":"Gyeonggi",
            "sub_region_code":"4182000000_Gyeonggi_Gapyeong",
            "shorten_url":"https:\/\/me2.do\/5S9oEjIS"
        },
        {
            "index":45,
            "sort":"education",
            "name":"가평설악엘크루",
            "search_code":"f9824",
            "apt_type":"분양(예정)",
            "apt_year":-2.0,
            "value_score":33.772,
            "region":"경기도 가평군",
            "region_code":"Gyeonggi",
            "sub_region_code":"4182000000_Gyeonggi_Gapyeong",
            "shorten_url":"https:\/\/me2.do\/5S9oEjIS"
        },
        {
            "index":46,
            "sort":"education",
            "name":"청평세양청마루",
            "search_code":"25840",
            "apt_type":"아파트",
            "apt_year":17.0,
            "value_score":33.7,
            "region":"경기도 가평군",
            "region_code":"Gyeonggi",
            "sub_region_code":"4182000000_Gyeonggi_Gapyeong",
            "shorten_url":"https:\/\/me2.do\/5S9oEjIS"
        },
        {
            "index":47,
            "sort":"education",
            "name":"청평경남아너스빌",
            "search_code":"25896",
            "apt_type":"아파트",
            "apt_year":16.0,
            "value_score":33.1,
            "region":"경기도 가평군",
            "region_code":"Gyeonggi",
            "sub_region_code":"4182000000_Gyeonggi_Gapyeong",
            "shorten_url":"https:\/\/me2.do\/5S9oEjIS"
        },
        {
            "index":48,
            "sort":"education",
            "name":"가평블루핀",
            "search_code":"122643",
            "apt_type":"아파트",
            "apt_year":5.0,
            "value_score":32.524,
            "region":"경기도 가평군",
            "region_code":"Gyeonggi",
            "sub_region_code":"4182000000_Gyeonggi_Gapyeong",
            "shorten_url":"https:\/\/me2.do\/5S9oEjIS"
        },
        {
            "index":49,
            "sort":"education",
            "name":"태광",
            "search_code":"15866",
            "apt_type":"아파트",
            "apt_year":32.0,
            "value_score":31.824,
            "region":"경기도 가평군",
            "region_code":"Gyeonggi",
            "sub_region_code":"4182000000_Gyeonggi_Gapyeong",
            "shorten_url":"https:\/\/me2.do\/5S9oEjIS"
        }
    ]
}