{
    "schema":{
        "fields":[
            {
                "name":"index",
                "type":"integer"
            },
            {
                "name":"거래금액",
                "type":"string"
            },
            {
                "name":"거래유형",
                "type":"string"
            },
            {
                "name":"건축년도",
                "type":"number"
            },
            {
                "name":"년",
                "type":"integer"
            },
            {
                "name":"도로명",
                "type":"string"
            },
            {
                "name":"도로명건물본번호코드",
                "type":"number"
            },
            {
                "name":"도로명건물부번호코드",
                "type":"number"
            },
            {
                "name":"도로명시군구코드",
                "type":"number"
            },
            {
                "name":"도로명일련번호코드",
                "type":"number"
            },
            {
                "name":"도로명코드",
                "type":"number"
            },
            {
                "name":"동",
                "type":"number"
            },
            {
                "name":"등기일자",
                "type":"number"
            },
            {
                "name":"매도자",
                "type":"string"
            },
            {
                "name":"매수자",
                "type":"string"
            },
            {
                "name":"법정동",
                "type":"string"
            },
            {
                "name":"법정동본번코드",
                "type":"number"
            },
            {
                "name":"법정동부번코드",
                "type":"number"
            },
            {
                "name":"법정동시군구코드",
                "type":"number"
            },
            {
                "name":"법정동읍면동코드",
                "type":"number"
            },
            {
                "name":"법정동지번코드",
                "type":"number"
            },
            {
                "name":"아파트",
                "type":"string"
            },
            {
                "name":"월",
                "type":"integer"
            },
            {
                "name":"일",
                "type":"integer"
            },
            {
                "name":"일련번호",
                "type":"string"
            },
            {
                "name":"전용면적",
                "type":"number"
            },
            {
                "name":"중개사소재지",
                "type":"string"
            },
            {
                "name":"지번",
                "type":"string"
            },
            {
                "name":"지역코드",
                "type":"integer"
            },
            {
                "name":"층",
                "type":"integer"
            },
            {
                "name":"해제사유발생일",
                "type":"number"
            },
            {
                "name":"해제여부",
                "type":"number"
            },
            {
                "name":"도로명지상지하코드",
                "type":"number"
            },
            {
                "name":"history_date",
                "type":"string"
            },
            {
                "name":"history_price",
                "type":"string"
            },
            {
                "name":"history_floor",
                "type":"string"
            },
            {
                "name":"graph_history_date",
                "type":"string"
            },
            {
                "name":"graph_history_price",
                "type":"string"
            },
            {
                "name":"max_price",
                "type":"string"
            },
            {
                "name":"min_price_from_2019",
                "type":"string"
            },
            {
                "name":"code",
                "type":"number"
            },
            {
                "name":"y",
                "type":"number"
            },
            {
                "name":"x",
                "type":"number"
            },
            {
                "name":"rank_info",
                "type":"string"
            },
            {
                "name":"sURL",
                "type":"string"
            },
            {
                "name":"type",
                "type":"string"
            },
            {
                "name":"구분",
                "type":"number"
            }
        ],
        "primaryKey":[
            "index"
        ],
        "pandas_version":"0.20.0"
    },
    "data":[
        {
            "index":0,
            "거래금액":"23,300",
            "거래유형":"중개거래",
            "건축년도":2001.0,
            "년":2024,
            "도로명":"능곡로",
            "도로명건물본번호코드":8.0,
            "도로명건물부번호코드":0.0,
            "도로명시군구코드":41150.0,
            "도로명일련번호코드":1.0,
            "도로명코드":3181009.0,
            "동":null,
            "등기일자":null,
            "매도자":"개인",
            "매수자":"개인",
            "법정동":"신곡동",
            "법정동본번코드":754.0,
            "법정동부번코드":0.0,
            "법정동시군구코드":41150.0,
            "법정동읍면동코드":10400.0,
            "법정동지번코드":1.0,
            "아파트":"신곡주공4",
            "월":8,
            "일":16,
            "일련번호":"41150-84",
            "전용면적":59.47,
            "중개사소재지":"경기 의정부시",
            "지번":754,
            "지역코드":41150,
            "층":19,
            "해제사유발생일":null,
            "해제여부":null,
            "도로명지상지하코드":0.0,
            "history_date":"['2019-01-02', '2019-01-07', '2019-01-08', '2019-01-16', '2019-01-31', '2019-02-01', '2019-02-28', '2019-03-07', '2019-03-30', '2019-04-22', '2019-05-02', '2019-05-03', '2019-05-10', '2019-05-17', '2019-05-17', '2019-06-07', '2019-06-16', '2019-06-19', '2019-07-01', '2019-07-02', '2019-07-03', '2019-07-05', '2019-07-22', '2019-08-05', '2019-08-15', '2019-09-10', '2019-09-17', '2019-09-28', '2019-10-04', '2019-10-09', '2019-10-14', '2019-10-16', '2019-10-25', '2019-10-29', '2019-10-29', '2019-11-11', '2019-12-12', '2020-01-03', '2020-01-15', '2020-01-20', '2020-02-18', '2020-02-20', '2020-03-02', '2020-03-02', '2020-03-04', '2020-03-09', '2020-03-13', '2020-03-18', '2020-04-01', '2020-04-03', '2020-04-06', '2020-04-16', '2020-04-20', '2020-05-05', '2020-05-13', '2020-05-17', '2020-05-27', '2020-05-30', '2020-06-17', '2020-06-25', '2020-07-02', '2020-07-08', '2020-07-19', '2020-07-30', '2020-08-07', '2020-08-15', '2020-08-17', '2020-08-17', '2020-08-27', '2020-08-28', '2020-09-07', '2020-09-17', '2020-09-22', '2020-09-22', '2020-09-26', '2020-10-12', '2020-10-13', '2020-10-16', '2020-10-17', '2020-10-19', '2020-10-20', '2020-10-24', '2020-10-26', '2020-10-31', '2020-11-03', '2020-11-09', '2020-11-14', '2020-11-18', '2020-11-18', '2020-11-24', '2020-11-24', '2020-11-27', '2020-11-29', '2020-12-07', '2020-12-13', '2020-12-19', '2020-12-25', '2020-12-26', '2020-12-31', '2021-01-05', '2021-01-07', '2021-01-19', '2021-01-22', '2021-01-29', '2021-02-03', '2021-02-05', '2021-02-11', '2021-02-16', '2021-02-16', '2021-02-17', '2021-02-18', '2021-02-18', '2021-02-22', '2021-02-22', '2021-02-25', '2021-03-03', '2021-03-04', '2021-03-05', '2021-03-11', '2021-03-23', '2021-04-01', '2021-04-14', '2021-04-30', '2021-05-10', '2021-05-12', '2021-05-14', '2021-05-27', '2021-05-28', '2021-06-05', '2021-06-07', '2021-06-28', '2021-07-01', '2021-07-06', '2021-07-06', '2021-07-08', '2021-07-13', '2021-08-17', '2021-08-18', '2021-08-24', '2021-08-31', '2021-09-15', '2021-10-05', '2021-10-20', '2021-11-09', '2021-11-12', '2021-11-23', '2021-12-02', '2021-12-03', '2021-12-14', '2021-12-31', '2022-01-10', '2022-02-07', '2022-02-08', '2022-02-08', '2022-02-13', '2022-03-03', '2022-04-14', '2022-05-18', '2022-05-24', '2022-08-09', '2022-08-16', '2022-12-19', '2023-02-14', '2023-03-22', '2023-04-15', '2023-04-15', '2023-04-19', '2023-04-22', '2023-05-13', '2023-05-31', '2023-06-12', '2023-08-04', '2023-08-24', '2023-08-31', '2023-09-15', '2023-09-23', '2023-09-24', '2023-09-25', '2023-09-26', '2023-10-07', '2023-10-07', '2023-10-22', '2023-10-24', '2023-10-28', '2023-11-21', '2023-11-23', '2024-02-03', '2024-02-12', '2024-04-29', '2024-05-02', '2024-05-08', '2024-05-13', '2024-05-16', '2024-06-06', '2024-06-10', '2024-06-19', '2024-06-22', '2024-07-13', '2024-08-05', '2024-08-12', '2024-09-04', '2024-09-05']",
            "history_price":"['18500', '21100', '18800', '17600', '17000', '19500', '18400', '20000', '17500', '18000', '17500', '19400', '18500', '17500', '19800', '17300', '17700', '18000', '19000', '18450', '17400', '18350', '17700', '19000', '18400', '18700', '17400', '18300', '16700', '18400', '19700', '18600', '18500', '18500', '18000', '17000', '18300', '18200', '18200', '18700', '19450', '19200', '18700', '18700', '20000', '19300', '18500', '20000', '18000', '18500', '18800', '17800', '18000', '18500', '20700', '18500', '19850', '18200', '18850', '21000', '18300', '20800', '18800', '18300', '20300', '18500', '20500', '20500', '19750', '17000', '18000', '18500', '20300', '20300', '19000', '19800', '18500', '17850', '17500', '18200', '19800', '18500', '18000', '18500', '19000', '19900', '21200', '17800', '19800', '18500', '19400', '19300', '18700', '19800', '20500', '22700', '21000', '20500', '21000', '20400', '18700', '21000', '24700', '22700', '24000', '18000', '23000', '25000', '21000', '24000', '22500', '25000', '24000', '25000', '25500', '24000', '25000', '24000', '24300', '26500', '25500', '26000', '24400', '25300', '26700', '25500', '26500', '29000', '27200', '24000', '30000', '28000', '29500', '31000', '27000', '32000', '27800', '32000', '32000', '25000', '34000', '33500', '32800', '33000', '34500', '33400', '32000', '31500', '31600', '33500', '31000', '33000', '32500', '30000', '32500', '34900', '32900', '30000', '31000', '30000', '30000', '25000', '29000', '24800', '23000', '23000', '23000', '23500', '24050', '24000', '24500', '25000', '23500', '25000', '23000', '25300', '23500', '26500', '25500', '25500', '25500', '25600', '27500', '27000', '26700', '23000', '28900', '26700', '23000', '24400', '24500', '24300', '23000', '22000', '23450', '23000', '26000', '22800', '20500', '20500', '22700', '21000']",
            "history_floor":"['12', '8', '18', '2', '2', '4', '20', '15', '15', '11', '17', '13', '6', '19', '14', '14', '3', '4', '11', '12', '4', '4', '12', '10', '24', '22', '2', '1', '4', '17', '15', '17', '19', '25', '12', '25', '15', '10', '3', '22', '11', '7', '17', '17', '9', '16', '18', '21', '16', '9', '19', '7', '4', '21', '22', '12', '14', '12', '16', '21', '17', '23', '14', '9', '15', '12', '10', '16', '11', '2', '6', '15', '11', '11', '14', '14', '12', '5', '1', '25', '8', '2', '2', '6', '8', '18', '7', '25', '12', '3', '12', '12', '3', '4', '7', '16', '18', '10', '25', '23', '3', '12', '23', '8', '15', '18', '2', '8', '1', '6', '4', '11', '16', '23', '24', '5', '5', '2', '3', '4', '17', '3', '18', '12', '11', '24', '14', '22', '4', '1', '7', '16', '11', '10', '3', '13', '2', '17', '10', '1', '7', '20', '13', '15', '9', '10', '8', '10', '7', '4', '12', '15', '8', '20', '10', '22', '2', '16', '22', '3', '3', '8', '14', '7', '13', '13', '8', '5', '13', '15', '5', '14', '11', '8', '13', '15', '6', '20', '16', '15', '15', '11', '23', '19', '5', '3', '7', '4', '16', '17', '21', '25', '13', '25', '18', '5', '11', '6', '2', '1', '9', '12']",
            "graph_history_date":"['2019-01', '2019-02', '2019-03', '2019-04', '2019-05', '2019-06', '2019-07', '2019-08', '2019-09', '2019-10', '2019-11', '2019-12', '2020-01', '2020-02', '2020-03', '2020-04', '2020-05', '2020-06', '2020-07', '2020-08', '2020-09', '2020-10', '2020-11', '2020-12', '2021-01', '2021-02', '2021-03', '2021-04', '2021-05', '2021-06', '2021-07', '2021-08', '2021-09', '2021-10', '2021-11', '2021-12', '2022-01', '2022-02', '2022-03', '2022-04', '2022-05', '2022-06', '2022-07', '2022-08', '2022-09', '2022-10', '2022-11', '2022-12', '2023-01', '2023-02', '2023-03', '2023-04', '2023-05', '2023-06', '2023-07', '2023-08', '2023-09', '2023-10', '2023-11', '2023-12', '2024-01', '2024-02', '2024-03', '2024-04', '2024-05', '2024-06', '2024-07', '2024-08', '2024-09', '2024-10']",
            "graph_history_price":"[18600.0, 18950.0, 18750.0, 18000.0, 18540.0, 17666.666666666668, 18180.0, 18700.0, 18133.333333333332, 18342.85714285714, 17000.0, 18300.0, 18366.666666666668, 19325.0, 19200.0, 18220.0, 19150.0, 19925.0, 19050.0, 19425.0, 19220.0, 18516.666666666668, 19288.88888888889, 20916.666666666668, 21500.0, 23363.636363636364, 24760.0, 25300.0, 26600.0, 27066.666666666668, 29500.0, 29200.0, 34000.0, 33150.0, 33633.333333333336, 32150.0, 31000.0, 32000.0, 34900.0, 32900.0, 30500.0, 30500.0, 30500.0, 30000.0, 30000.0, 30000.0, 30000.0, 25000.0, 25000.0, 29000.0, 24800.0, 23125.0, 24025.0, 24500.0, 24500.0, 24500.0, 24760.0, 26220.0, 24850.0, 24850.0, 24850.0, 27800.0, 27800.0, 23000.0, 24050.0, 23612.5, 22800.0, 20500.0, 21850.0, 21850.0]",
            "max_price":"['2022-03-03', '34900']",
            "min_price_from_2019":"['2019-10-04', '16700']",
            "code":8202.0,
            "y":37.738888,
            "x":127.05891,
            "rank_info":"[224.0, 95.0, 45.4942]",
            "sURL":"https:\/\/me2.do\/GHvMZFPz",
            "type":"TRADE",
            "구분":null
        }
    ]
}